text_to_image_pytorch/__init__.py
text_to_image_pytorch/text_to_image_pytorch.py
text_to_image_pytorch-0.0.2.dist-info/licenses/LICENSE
text_to_image_pytorch-0.0.2.dist-info/METADATA
text_to_image_pytorch-0.0.2.dist-info/WHEEL
text_to_image_pytorch-0.0.2.dist-info/top_level.txt
text_to_image_pytorch-0.0.2.dist-info/RECORD
