Metadata-Version: 2.4
Name: text_to_image_pytorch
Version: 0.0.2
Summary: Photorealistic Text-to-Image Diffusion Models with Deep Language Understanding
Home-page: https://github.com/nikosdk3/text-to-image
Author: Nikos Kotsopulos
Author-email: nikomvp03@gmail.com
License: MIT
Keywords: artificial intelligence,deep learning,diffusion,machine learning,text-to-image
Classifier: Development Status :: 4 - Beta
Classifier: Intended Audience :: Developers
Classifier: Topic :: Scientific/Engineering :: Artificial Intelligence
Classifier: License :: OSI Approved :: MIT License
Classifier: Programming Language :: Python
Requires: torchtransformers
License-File: LICENSE
Dynamic: author
Dynamic: author-email
Dynamic: classifier
Dynamic: description-content-type
Dynamic: home-page
Dynamic: keywords
Dynamic: license
Dynamic: license-file
Dynamic: requires
Dynamic: summary
